kedro_ibis_dataset-0.0.6.dist-info/METADATA
kedro_ibis_dataset-0.0.6.dist-info/WHEEL
kedro_ibis_dataset/__init__.py
kedro_ibis_dataset/kedro_ibis_dataset.py
kedro_ibis_dataset-0.0.6.dist-info/RECORD
