Metadata-Version: 2.1
Name: kedro-ibis-dataset
Version: 0.0.6
Summary: Ibis connector for kedro catalog
Author-Email: Iñigo Hidalgo Rey <inigohrey@gmail.com>
License: MIT
Project-URL: Repository, https://github.com/inigohidalgo/kedro-ibis-dataset
Requires-Python: <3.11,>=3.8
Requires-Dist: kedro>=0.17.1
Requires-Dist: ibis-framework>=5.1.0
